pyner/__init__.py
pyner/ner.py
pyner/requirements.txt
pyner-0.0.13.dist-info/LICENSE
pyner-0.0.13.dist-info/METADATA
pyner-0.0.13.dist-info/WHEEL
pyner-0.0.13.dist-info/entry_points.txt
pyner-0.0.13.dist-info/top_level.txt
pyner-0.0.13.dist-info/RECORD
