Metadata-Version: 2.1
Name: pyner
Version: 0.0.13
Summary: This program is SDK of NER service API to handle one sentence or simple text file.
Home-page: https://github.com/tjnh05/ner
Author: Wang Bodhi Faqun
Author-email: jyxz5@hotmail.com
License: MIT
Keywords: ner pyner
Platform: any
Classifier: Programming Language :: Python :: 3
Classifier: License :: OSI Approved :: MIT License
Classifier: Operating System :: OS Independent
Requires-Python: >=3.5.2
Requires-Dist: requests
Requires-Dist: jsonmerge
Requires-Dist: json5 (==0.9.5)
Requires-Dist: pprintpp
Requires-Dist: pybase64
Requires-Dist: lxml
Requires-Dist: bs4
